dlt_source_slack/__init__.py
dlt_source_slack/manifest.yml
dlt_source_slack/web_client.py
dlt_source_slack/tests/__init__.py
dlt_source_slack/tests/test_noop.py
dlt_source_slack-0.0.2.dist-info/METADATA
dlt_source_slack-0.0.2.dist-info/WHEEL
dlt_source_slack-0.0.2.dist-info/licenses/LICENSE
dlt_source_slack-0.0.2.dist-info/RECORD
