Metadata-Version: 2.4
Name: dlt-source-slack
Version: 0.0.2
Summary: DLT (dlthub.com) source for Slack (slack.com)
Author: Planet A Ventures
Maintainer-email: Joscha Feth <joscha@planet-a.com>
License: MIT
License-File: LICENSE
Keywords: dlt,dlthub,slack
Classifier: Development Status :: 4 - Beta
Classifier: Intended Audience :: Developers
Classifier: License :: OSI Approved :: MIT License
Classifier: Programming Language :: Python :: 3
Classifier: Programming Language :: Python :: 3.12
Classifier: Programming Language :: Python :: 3.13
Requires-Python: >=3.12
Requires-Dist: dlt>=1.9.0
Requires-Dist: slack-sdk>=3.35.0
Provides-Extra: show
Requires-Dist: dlt[duckdb]>=1.9.0; extra == 'show'
Requires-Dist: streamlit>=1.41.1; extra == 'show'
Requires-Dist: watchdog>=6.0.0; extra == 'show'
